connection_restapi_client_poc/__init__.py
connection_restapi_client_poc/api_client.py
connection_restapi_client_poc/api_response.py
connection_restapi_client_poc/configuration.py
connection_restapi_client_poc/exceptions.py
connection_restapi_client_poc/ideastatica_client.py
connection_restapi_client_poc/py.typed
connection_restapi_client_poc/rest.py
connection_restapi_client_poc/api/__init__.py
connection_restapi_client_poc/api/calculation_api.py
connection_restapi_client_poc/api/client_api.py
connection_restapi_client_poc/api/connection_api.py
connection_restapi_client_poc/api/export_api.py
connection_restapi_client_poc/api/load_effect_api.py
connection_restapi_client_poc/api/material_api.py
connection_restapi_client_poc/api/member_api.py
connection_restapi_client_poc/api/operation_api.py
connection_restapi_client_poc/api/parameter_api.py
connection_restapi_client_poc/api/presentation_api.py
connection_restapi_client_poc/api/project_api.py
connection_restapi_client_poc/api/report_api.py
connection_restapi_client_poc/api/template_api.py
connection_restapi_client_poc/models/__init__.py
connection_restapi_client_poc/models/anchor3_d.py
connection_restapi_client_poc/models/anchor_grid.py
connection_restapi_client_poc/models/anchor_type.py
connection_restapi_client_poc/models/arc_segment3_d.py
connection_restapi_client_poc/models/base_plate3_d.py
connection_restapi_client_poc/models/base_template_conversion.py
connection_restapi_client_poc/models/beam.py
connection_restapi_client_poc/models/beam_data.py
connection_restapi_client_poc/models/bend_data.py
connection_restapi_client_poc/models/bolt_grid.py
connection_restapi_client_poc/models/bolt_shear_type.py
connection_restapi_client_poc/models/buckling_res.py
connection_restapi_client_poc/models/check_member.py
connection_restapi_client_poc/models/check_res_anchor.py
connection_restapi_client_poc/models/check_res_bolt.py
connection_restapi_client_poc/models/check_res_concrete_block.py
connection_restapi_client_poc-24.0.6.782.dist-info/METADATA
connection_restapi_client_poc-24.0.6.782.dist-info/WHEEL
connection_restapi_client_poc-24.0.6.782.dist-info/top_level.txt
connection_restapi_client_poc-24.0.6.782.dist-info/RECORD
