Metadata-Version: 2.1
Name: connection-restapi-client-poc
Version: 24.0.6.782
Summary: Connection Rest API 1.0
Home-page: UNKNOWN
Author: OpenAPI Generator community
Author-email: team@openapitools.org
License: UNKNOWN
Keywords: OpenAPI,OpenAPI-Generator,Connection Rest API 1.0
Platform: UNKNOWN
Requires-Dist: urllib3<3.0.0,>=1.25.3
Requires-Dist: python-dateutil
Requires-Dist: pydantic>=2
Requires-Dist: typing-extensions>=4.7.1
